Workbook
Name CodeP: Table2[Product_Code]
Name Cust_ID: customersdata[Cust_ID]
Name Product_Code: Table3[Product_Code]
Name Productcode: Table2[Product_Code]
Name productdata: Table2[]
Name purchasedata: Table4[]
Name Slicer_Product_Name: #N/A
Name vendorsdata: Table3[]

Sheet DASHBOARD
R10: Notification !
R11: {=_xlfn._xlws.FILTER(Table6[Notification],Table6[Notification]<>"")} -> 📞 Laptop HP Needs to re-order ! Ph 0321xxxxxxxx
R12: 📞 Wireless Printer Needs to re-order ! Ph 0321xxxxxxxx
R13: 📞 Desktop Needs to re-order ! Ph 0333xxxxxxxx
R14: 📞 Adopter Needs to re-order ! Ph 0317xxxxxxxx

Sheet CUSTOMERS
D5: Cust_ID | E5: Cust_Name | F5: Email | G5: Address
D6: 101 | E6: Ali | F6: ali@gmail.com | G6: Karachi, Pakistan
D7: 102 | E7: Ahmed | F7: ahmed@gmail.com | G7: Karachi, Pakistan
D8: 103 | E8: Ahad | F8: ahad@gmail.com | G8: Karachi, Pakistan
D9: 104 | E9: Bilal | F9: bilal@gmail.com | G9: Karachi, Pakistan
D10: 105 | E10: Hamid | F10: hamid@gmail.com | G10: Karachi, Pakistan
D11: 106 | E11: Danish | F11: danish@gmail.com | G11: Karachi, Pakistan
D12: 107 | E12: Waleed | F12: waleed@gmail.com | G12: Karachi, Pakistan
D13: 108 | E13: Qsim | F13: qasim@gmail.com | G13: Karachi, Pakistan

Sheet PRODUCTS
D5: Product_Code | E5: Product_Name | F5: Cost | G5: Selling_Price
D6: N101 | E6: Smart Watch | F6: 980 | G6: 1200
D7: N102 | E7: Laptop HP | F7: 34500 | G7: 50000
D8: N103 | E8: Wireless Printer | F8: 35650 | G8: 55000
D9: N104 | E9: Desktop | F9: 21000 | G9: 35000
D10: N105 | E10: Mouse | F10: 550 | G10: 1100
D11: N106 | E11: Rgb Keyboard | F11: 1250 | G11: 2000
D12: N107 | E12: Camera | F12: 52000 | G12: 75000
D13: N108 | E13: Headphone | F13: 790 | G13: 1800
D14: N109 | E14: Speakers | F14: 1750 | G14: 3500
D15: N110 | E15: Tablets | F15: 23500 | G15: 45000
D16: N111 | E16: Adopter | F16: 1250 | G16: 2500
D17: N112 | E17: Wireless Mouse | F17: 2500 | G17: 4000
... D24: N120 | E24: Tripod | F24: 800 | G24: 2400

Sheet VENDORS
D5: Product_Code | E5: Product_Name | F5: Vendor_ Name | G5: Phone_No | H5: Address
D6: N101 | E6: Smart Watch | F6: Wahaj | G6: 0321xxxxxxxx | H6: Karachi, Pakistan.
D7: N102 | E7: Laptop HP | F7: Hanif | G7: 0321xxxxxxxx | H7: Karachi, Pakistan.
D8: N103 | E8: Wireless Printer | F8: Fahad | G8: 0321xxxxxxxx | H8: Karachi, Pakistan.
D9: N104 | E9: Desktop | F9: Kareem | G9: 0333xxxxxxxx | H9: Karachi, Pakistan.
D10: N105 | E10: Mouse | F10: Hammad | G10: 0333xxxxxxxx | H10: Karachi, Pakistan.
D11: N106 | E11: Rgb Keyboard | F11: Yasir | G11: 0333xxxxxxxx | H11: Karachi, Pakistan.
D12: N107 | E12: Camera | F12: Tahir | G12: 0333xxxxxxxx | H12: Karachi, Pakistan.
D13: N108 | E13: Headphone | F13: Faizan | G13: 0314xxxxxxxx | H13: Karachi, Pakistan.
D14: N109 | E14: Speakers | F14: Rashid | G14: 0314xxxxxxxx | H14: Karachi, Pakistan.
D15: N110 | E15: Tablets | F15: Saad | G15: 0314xxxxxxxx | H15: Karachi, Pakistan.
D16: N111 | E16: Adopter | F16: Affan | G16: 0317xxxxxxxx | H16: Karachi, Pakistan.
... D23: N119 | E23: Iphone 14 | F23: Ebaad | G23: 0348xxxxxxxx | H23: Karachi, Pakistan.

Sheet NEW ENTRY
D5: Prchase_Entry | H5: Sales_Entry

Sheet PURCHASE
D5: Product_Code | E5: Product_Name | F5: Vendors | G5: Date | H5: Units | I5: Cost | J5: Amount
D6: N111 | E6: =IFERROR(VLOOKUP(PURCHASE!$D6,Table2[#All],2,0),"") -> Adopter | F6: =IFERROR(VLOOKUP(PURCHASE!$D6,Table3[#All],3,0),"") -> Affan | G6: 45936 | H6: 10 | I6: =IFERROR(VLOOKUP(PURCHASE!$D6,Table2[#All],3,0),"") -> 1250 | J6: =Table4[[#This Row],[Units]]*Table4[[#This Row],[Cost]] -> 12500
D7: N113 | E7: =IFERROR(VLOOKUP(PURCHASE!$D7,Table2[#All],2,0),"") -> Macbook | F7: =IFERROR(VLOOKUP(PURCHASE!$D7,Table3[#All],3,0),"") -> Sarim | G7: 45937 | H7: 25 | I7: =IFERROR(VLOOKUP(PURCHASE!$D7,Table2[#All],3,0),"") -> 150000 | J7: =Table4[[#This Row],[Units]]*Table4[[#This Row],[Cost]] -> 3750000
D8: N114 | E8: =IFERROR(VLOOKUP(PURCHASE!$D8,Table2[#All],2,0),"") -> Charger | F8: =IFERROR(VLOOKUP(PURCHASE!$D8,Table3[#All],3,0),"") -> Rayyan | G8: 45939 | H8: 50 | I8: =IFERROR(VLOOKUP(PURCHASE!$D8,Table2[#All],3,0),"") -> 450 | J8: =Table4[[#This Row],[Units]]*Table4[[#This Row],[Cost]] -> 22500
D9: N104 | E9: =IFERROR(VLOOKUP(PURCHASE!$D9,Table2[#All],2,0),"") -> Desktop | F9: =IFERROR(VLOOKUP(PURCHASE!$D9,Table3[#All],3,0),"") -> Kareem | G9: 45940 | H9: 10 | I9: =IFERROR(VLOOKUP(PURCHASE!$D9,Table2[#All],3,0),"") -> 21000 | J9: =Table4[[#This Row],[Units]]*Table4[[#This Row],[Cost]] -> 210000
D10: N102 | E10: =IFERROR(VLOOKUP(PURCHASE!$D10,Table2[#All],2,0),"") -> Laptop HP | F10: =IFERROR(VLOOKUP(PURCHASE!$D10,Table3[#All],3,0),"") -> Hanif | G10: 45936 | H10: 15 | I10: =IFERROR(VLOOKUP(PURCHASE!$D10,Table2[#All],3,0),"") -> 34500 | J10: =Table4[[#This Row],[Units]]*Table4[[#This Row],[Cost]] -> 517500
D11: N105 | E11: =IFERROR(VLOOKUP(PURCHASE!$D11,Table2[#All],2,0),"") -> Mouse | F11: =IFERROR(VLOOKUP(PURCHASE!$D11,Table3[#All],3,0),"") -> Hammad | G11: 45937 | H11: 25 | I11: =IFERROR(VLOOKUP(PURCHASE!$D11,Table2[#All],3,0),"") -> 550 | J11: =Table4[[#This Row],[Units]]*Table4[[#This Row],[Cost]] -> 13750
D12: N106 | E12: =IFERROR(VLOOKUP(PURCHASE!$D12,Table2[#All],2,0),"") -> Rgb Keyboard | F12: =IFERROR(VLOOKUP(PURCHASE!$D12,Table3[#All],3,0),"") -> Yasir | G12: 45939 | H12: 32 | I12: =IFERROR(VLOOKUP(PURCHASE!$D12,Table2[#All],3,0),"") -> 1250 | J12: =Table4[[#This Row],[Units]]*Table4[[#This Row],[Cost]] -> 40000
D13: N101 | E13: =IFERROR(VLOOKUP(PURCHASE!$D13,Table2[#All],2,0),"") -> Smart Watch | F13: =IFERROR(VLOOKUP(PURCHASE!$D13,Table3[#All],3,0),"") -> Wahaj | G13: 45940 | H13: 60 | I13: =IFERROR(VLOOKUP(PURCHASE!$D13,Table2[#All],3,0),"") -> 980 | J13: =Table4[[#This Row],[Units]]*Table4[[#This Row],[Cost]] -> 58800
D14: N103 | E14: =IFERROR(VLOOKUP(PURCHASE!$D14,Table2[#All],2,0),"") -> Wireless Printer | F14: =IFERROR(VLOOKUP(PURCHASE!$D14,Table3[#All],3,0),"") -> Fahad | G14: 45936 | H14: 12 | I14: =IFERROR(VLOOKUP(PURCHASE!$D14,Table2[#All],3,0),"") -> 35650 | J14: =Table4[[#This Row],[Units]]*Table4[[#This Row],[Cost]] -> 427800
D15: N108 | E15: =IFERROR(VLOOKUP(PURCHASE!$D15,Table2[#All],2,0),"") -> Headphone | F15: =IFERROR(VLOOKUP(PURCHASE!$D15,Table3[#All],3,0),"") -> Faizan | G15: 45937 | H15: 35 | I15: =IFERROR(VLOOKUP(PURCHASE!$D15,Table2[#All],3,0),"") -> 790 | J15: =Table4[[#This Row],[Units]]*Table4[[#This Row],[Cost]] -> 27650
D16: N110 | E16: =IFERROR(VLOOKUP(PURCHASE!$D16,Table2[#All],2,0),"") -> Tablets | F16: =IFERROR(VLOOKUP(PURCHASE!$D16,Table3[#All],3,0),"") -> Saad | G16: 45939 | H16: 23 | I16: =IFERROR(VLOOKUP(PURCHASE!$D16,Table2[#All],3,0),"") -> 23500 | J16: =Table4[[#This Row],[Units]]*Table4[[#This Row],[Cost]] -> 540500
D17: N107 | E17: =IFERROR(VLOOKUP(PURCHASE!$D17,Table2[#All],2,0),"") -> Camera | F17: =IFERROR(VLOOKUP(PURCHASE!$D17,Table3[#All],3,0),"") -> Tahir | G17: 45940 | H17: 20 | I17: =IFERROR(VLOOKUP(PURCHASE!$D17,Table2[#All],3,0),"") -> 52000 | J17: =Table4[[#This Row],[Units]]*Table4[[#This Row],[Cost]] -> 1040000
... D24: N101 | E24: =IFERROR(VLOOKUP(PURCHASE!$D24,Table2[#All],2,0),"") -> Smart Watch | F24: =IFERROR(VLOOKUP(PURCHASE!$D24,Table3[#All],3,0),"") -> Wahaj | G24: 45937 | H24: 12 | I24: =IFERROR(VLOOKUP(PURCHASE!$D24,Table2[#All],3,0),"") -> 980 | J24: =Table4[[#This Row],[Units]]*Table4[[#This Row],[Cost]] -> 11760

Sheet SALES
D5: Cust_ID | E5: Cust_Name | F5: Product_Code | G5: Product_Name | H5: Date | I5: Stock(Units) | J5: Units | K5: Price | L5: Amount
D6: 102 | E6: =IFERROR(VLOOKUP(salesdata[[#This Row],[Cust_ID]],customersdata[#All],2,0),"") -> Ahmed | F6: N105 | G6: =IFERROR(VLOOKUP(salesdata[[#This Row],[Product_Code]],Table2[#All],2,0),"") -> Mouse | H6: 45936 | I6: =IFERROR(VLOOKUP(salesdata[[#This Row],[Product_Code]],Table6[#All],6,0),"") -> 23 | J6: 2 | K6: =IFERROR(VLOOKUP(salesdata[[#This Row],[Product_Code]],Table2[#All],4,0),"") -> 1100 | L6: =salesdata[[#This Row],[Units]]*salesdata[[#This Row],[Price]] -> 2200
D7: 105 | E7: =IFERROR(VLOOKUP(salesdata[[#This Row],[Cust_ID]],customersdata[#All],2,0),"") -> Hamid | F7: N104 | G7: =IFERROR(VLOOKUP(salesdata[[#This Row],[Product_Code]],Table2[#All],2,0),"") -> Desktop | H7: 45937 | I7: =IFERROR(VLOOKUP(salesdata[[#This Row],[Product_Code]],Table6[#All],6,0),"") -> 4 | J7: 6 | K7: =IFERROR(VLOOKUP(salesdata[[#This Row],[Product_Code]],Table2[#All],4,0),"") -> 35000 | L7: =salesdata[[#This Row],[Units]]*salesdata[[#This Row],[Price]] -> 210000
D8: 101 | E8: =IFERROR(VLOOKUP(salesdata[[#This Row],[Cust_ID]],customersdata[#All],2,0),"") -> Ali | F8: N102 | G8: =IFERROR(VLOOKUP(salesdata[[#This Row],[Product_Code]],Table2[#All],2,0),"") -> Laptop HP | H8: 45938 | I8: =IFERROR(VLOOKUP(salesdata[[#This Row],[Product_Code]],Table6[#All],6,0),"") -> 4 | J8: 11 | K8: =IFERROR(VLOOKUP(salesdata[[#This Row],[Product_Code]],Table2[#All],4,0),"") -> 50000 | L8: =salesdata[[#This Row],[Units]]*salesdata[[#This Row],[Price]] -> 550000
D9: 103 | E9: =IFERROR(VLOOKUP(salesdata[[#This Row],[Cust_ID]],customersdata[#All],2,0),"") -> Ahad | F9: N101 | G9: =IFERROR(VLOOKUP(salesdata[[#This Row],[Product_Code]],Table2[#All],2,0),"") -> Smart Watch | H9: 45939 | I9: =IFERROR(VLOOKUP(salesdata[[#This Row],[Product_Code]],Table6[#All],6,0),"") -> 71 | J9: 1 | K9: =IFERROR(VLOOKUP(salesdata[[#This Row],[Product_Code]],Table2[#All],4,0),"") -> 1200 | L9: =salesdata[[#This Row],[Units]]*salesdata[[#This Row],[Price]] -> 1200
D10: 104 | E10: =IFERROR(VLOOKUP(salesdata[[#This Row],[Cust_ID]],customersdata[#All],2,0),"") -> Bilal | F10: N103 | G10: =IFERROR(VLOOKUP(salesdata[[#This Row],[Product_Code]],Table2[#All],2,0),"") -> Wireless Printer | H10: 45940 | I10: =IFERROR(VLOOKUP(salesdata[[#This Row],[Product_Code]],Table6[#All],6,0),"") -> 4 | J10: 8 | K10: =IFERROR(VLOOKUP(salesdata[[#This Row],[Product_Code]],Table2[#All],4,0),"") -> 55000 | L10: =salesdata[[#This Row],[Units]]*salesdata[[#This Row],[Price]] -> 440000
D11: 107 | E11: =IFERROR(VLOOKUP(salesdata[[#This Row],[Cust_ID]],customersdata[#All],2,0),"") -> Waleed | F11: N107 | G11: =IFERROR(VLOOKUP(salesdata[[#This Row],[Product_Code]],Table2[#All],2,0),"") -> Camera | H11: 45941 | I11: =IFERROR(VLOOKUP(salesdata[[#This Row],[Product_Code]],Table6[#All],6,0),"") -> 13 | J11: 7 | K11: =IFERROR(VLOOKUP(salesdata[[#This Row],[Product_Code]],Table2[#All],4,0),"") -> 75000 | L11: =salesdata[[#This Row],[Units]]*salesdata[[#This Row],[Price]] -> 525000
D12: 106 | E12: =IFERROR(VLOOKUP(salesdata[[#This Row],[Cust_ID]],customersdata[#All],2,0),"") -> Danish | F12: N106 | G12: =IFERROR(VLOOKUP(salesdata[[#This Row],[Product_Code]],Table2[#All],2,0),"") -> Rgb Keyboard | H12: 45942 | I12: =IFERROR(VLOOKUP(salesdata[[#This Row],[Product_Code]],Table6[#All],6,0),"") -> 29 | J12: 3 | K12: =IFERROR(VLOOKUP(salesdata[[#This Row],[Product_Code]],Table2[#All],4,0),"") -> 2000 | L12: =salesdata[[#This Row],[Units]]*salesdata[[#This Row],[Price]] -> 6000
D13: 102 | E13: =IFERROR(VLOOKUP(salesdata[[#This Row],[Cust_ID]],customersdata[#All],2,0),"") -> Ahmed | F13: N109 | G13: =IFERROR(VLOOKUP(salesdata[[#This Row],[Product_Code]],Table2[#All],2,0),"") -> Speakers | H13: 45943 | I13: =IFERROR(VLOOKUP(salesdata[[#This Row],[Product_Code]],Table6[#All],6,0),"") -> 12 | J13: 2 | K13: =IFERROR(VLOOKUP(salesdata[[#This Row],[Product_Code]],Table2[#All],4,0),"") -> 3500 | L13: =salesdata[[#This Row],[Units]]*salesdata[[#This Row],[Price]] -> 7000
D14: 103 | E14: =IFERROR(VLOOKUP(salesdata[[#This Row],[Cust_ID]],customersdata[#All],2,0),"") -> Ahad | F14: N108 | G14: =IFERROR(VLOOKUP(salesdata[[#This Row],[Product_Code]],Table2[#All],2,0),"") -> Headphone | H14: 45944 | I14: =IFERROR(VLOOKUP(salesdata[[#This Row],[Product_Code]],Table6[#All],6,0),"") -> 34 | J14: 1 | K14: =IFERROR(VLOOKUP(salesdata[[#This Row],[Product_Code]],Table2[#All],4,0),"") -> 1800 | L14: =salesdata[[#This Row],[Units]]*salesdata[[#This Row],[Price]] -> 1800
D15: 101 | E15: =IFERROR(VLOOKUP(salesdata[[#This Row],[Cust_ID]],customersdata[#All],2,0),"") -> Ali | F15: N111 | G15: =IFERROR(VLOOKUP(salesdata[[#This Row],[Product_Code]],Table2[#All],2,0),"") -> Adopter | H15: 45945 | I15: =IFERROR(VLOOKUP(salesdata[[#This Row],[Product_Code]],Table6[#All],6,0),"") -> 4 | J15: 6 | K15: =IFERROR(VLOOKUP(salesdata[[#This Row],[Product_Code]],Table2[#All],4,0),"") -> 2500 | L15: =salesdata[[#This Row],[Units]]*salesdata[[#This Row],[Price]] -> 15000
D16: 106 | E16: =IFERROR(VLOOKUP(salesdata[[#This Row],[Cust_ID]],customersdata[#All],2,0),"") -> Danish | F16: N110 | G16: =IFERROR(VLOOKUP(salesdata[[#This Row],[Product_Code]],Table2[#All],2,0),"") -> Tablets | H16: 45946 | I16: =IFERROR(VLOOKUP(salesdata[[#This Row],[Product_Code]],Table6[#All],6,0),"") -> 21 | J16: 2 | K16: =IFERROR(VLOOKUP(salesdata[[#This Row],[Product_Code]],Table2[#All],4,0),"") -> 45000 | L16: =salesdata[[#This Row],[Units]]*salesdata[[#This Row],[Price]] -> 90000
D17: 107 | E17: =IFERROR(VLOOKUP(salesdata[[#This Row],[Cust_ID]],customersdata[#All],2,0),"") -> Waleed | F17: N112 | G17: =IFERROR(VLOOKUP(salesdata[[#This Row],[Product_Code]],Table2[#All],2,0),"") -> Wireless Mouse | H17: 45947 | I17: =IFERROR(VLOOKUP(salesdata[[#This Row],[Product_Code]],Table6[#All],6,0),"") -> 54 | J17: 3 | K17: =IFERROR(VLOOKUP(salesdata[[#This Row],[Product_Code]],Table2[#All],4,0),"") -> 4000 | L17: =salesdata[[#This Row],[Units]]*salesdata[[#This Row],[Price]] -> 12000
... D23: 108 | E23: =IFERROR(VLOOKUP(salesdata[[#This Row],[Cust_ID]],customersdata[#All],2,0),"") -> Qsim | F23: N119 | G23: =IFERROR(VLOOKUP(salesdata[[#This Row],[Product_Code]],Table2[#All],2,0),"") -> Iphone 14 | H23: 45949 | I23: =IFERROR(VLOOKUP(salesdata[[#This Row],[Product_Code]],Table6[#All],6,0),"") -> 13 | J23: 3 | K23: =IFERROR(VLOOKUP(salesdata[[#This Row],[Product_Code]],Table2[#All],4,0),"") -> 165000 | L23: =salesdata[[#This Row],[Units]]*salesdata[[#This Row],[Price]] -> 495000

Sheet INVENTORY
D6: Product_Code | E6: Product_Name | F6: Cost | G6: Purchased Units | H6: Sold Units | I6: Stock | J6: Stock Amount | K6: Notification
D7: =IFERROR(PRODUCTS!D6,"") -> N101 | E7: =IFERROR(PRODUCTS!E6,"") -> Smart Watch | F7: =IFERROR(PRODUCTS!F6,"") -> 980 | G7: =SUMIF(Table4[Product_Name],Table6[[#This Row],[Product_Name]],Table4[Units]) -> 72 | H7: =SUMIF(salesdata[Product_Name],Table6[[#This Row],[Product_Name]],salesdata[Units]) -> 1 | I7: =Table6[[#This Row],[Purchased Units]]-Table6[[#This Row],[Sold Units]] -> 71 | J7: =Table6[[#This Row],[Cost]]*Table6[[#This Row],[Stock]] -> 69580 | K7: =IF(Table6[[#This Row],[Stock]]<5,"📞 "&Table6[[#This Row],[Product_Name]]&" Needs to re-order ! Ph "&VLOOKUP(Table6[[#This Row],[Product_Code]],Table3[#All],4,0),"")
D8: =IFERROR(PRODUCTS!D7,"") -> N102 | E8: =IFERROR(PRODUCTS!E7,"") -> Laptop HP | F8: =IFERROR(PRODUCTS!F7,"") -> 34500 | G8: =SUMIF(Table4[Product_Name],Table6[[#This Row],[Product_Name]],Table4[Units]) -> 15 | H8: =SUMIF(salesdata[Product_Name],Table6[[#This Row],[Product_Name]],salesdata[Units]) -> 11 | I8: =Table6[[#This Row],[Purchased Units]]-Table6[[#This Row],[Sold Units]] -> 4 | J8: =Table6[[#This Row],[Cost]]*Table6[[#This Row],[Stock]] -> 138000 | K8: =IF(Table6[[#This Row],[Stock]]<5,"📞 "&Table6[[#This Row],[Product_Name]]&" Needs to re-order ! Ph "&VLOOKUP(Table6[[#This Row],[Product_Code]],Table3[#All],4,0),"") -> 📞 Laptop HP Needs to re-order ! Ph 0321xxxxxxxx
D9: =IFERROR(PRODUCTS!D8,"") -> N103 | E9: =IFERROR(PRODUCTS!E8,"") -> Wireless Printer | F9: =IFERROR(PRODUCTS!F8,"") -> 35650 | G9: =SUMIF(Table4[Product_Name],Table6[[#This Row],[Product_Name]],Table4[Units]) -> 12 | H9: =SUMIF(salesdata[Product_Name],Table6[[#This Row],[Product_Name]],salesdata[Units]) -> 8 | I9: =Table6[[#This Row],[Purchased Units]]-Table6[[#This Row],[Sold Units]] -> 4 | J9: =Table6[[#This Row],[Cost]]*Table6[[#This Row],[Stock]] -> 142600 | K9: =IF(Table6[[#This Row],[Stock]]<5,"📞 "&Table6[[#This Row],[Product_Name]]&" Needs to re-order ! Ph "&VLOOKUP(Table6[[#This Row],[Product_Code]],Table3[#All],4,0),"") -> 📞 Wireless Printer Needs to re-order ! Ph 0321xxxxxxxx
D10: =IFERROR(PRODUCTS!D9,"") -> N104 | E10: =IFERROR(PRODUCTS!E9,"") -> Desktop | F10: =IFERROR(PRODUCTS!F9,"") -> 21000 | G10: =SUMIF(Table4[Product_Name],Table6[[#This Row],[Product_Name]],Table4[Units]) -> 10 | H10: =SUMIF(salesdata[Product_Name],Table6[[#This Row],[Product_Name]],salesdata[Units]) -> 6 | I10: =Table6[[#This Row],[Purchased Units]]-Table6[[#This Row],[Sold Units]] -> 4 | J10: =Table6[[#This Row],[Cost]]*Table6[[#This Row],[Stock]] -> 84000 | K10: =IF(Table6[[#This Row],[Stock]]<5,"📞 "&Table6[[#This Row],[Product_Name]]&" Needs to re-order ! Ph "&VLOOKUP(Table6[[#This Row],[Product_Code]],Table3[#All],4,0),"") -> 📞 Desktop Needs to re-order ! Ph 0333xxxxxxxx
D11: =IFERROR(PRODUCTS!D10,"") -> N105 | E11: =IFERROR(PRODUCTS!E10,"") -> Mouse | F11: =IFERROR(PRODUCTS!F10,"") -> 550 | G11: =SUMIF(Table4[Product_Name],Table6[[#This Row],[Product_Name]],Table4[Units]) -> 25 | H11: =SUMIF(salesdata[Product_Name],Table6[[#This Row],[Product_Name]],salesdata[Units]) -> 2 | I11: =Table6[[#This Row],[Purchased Units]]-Table6[[#This Row],[Sold Units]] -> 23 | J11: =Table6[[#This Row],[Cost]]*Table6[[#This Row],[Stock]] -> 12650 | K11: =IF(Table6[[#This Row],[Stock]]<5,"📞 "&Table6[[#This Row],[Product_Name]]&" Needs to re-order ! Ph "&VLOOKUP(Table6[[#This Row],[Product_Code]],Table3[#All],4,0),"")
D12: =IFERROR(PRODUCTS!D11,"") -> N106 | E12: =IFERROR(PRODUCTS!E11,"") -> Rgb Keyboard | F12: =IFERROR(PRODUCTS!F11,"") -> 1250 | G12: =SUMIF(Table4[Product_Name],Table6[[#This Row],[Product_Name]],Table4[Units]) -> 32 | H12: =SUMIF(salesdata[Product_Name],Table6[[#This Row],[Product_Name]],salesdata[Units]) -> 3 | I12: =Table6[[#This Row],[Purchased Units]]-Table6[[#This Row],[Sold Units]] -> 29 | J12: =Table6[[#This Row],[Cost]]*Table6[[#This Row],[Stock]] -> 36250 | K12: =IF(Table6[[#This Row],[Stock]]<5,"📞 "&Table6[[#This Row],[Product_Name]]&" Needs to re-order ! Ph "&VLOOKUP(Table6[[#This Row],[Product_Code]],Table3[#All],4,0),"")
D13: =IFERROR(PRODUCTS!D12,"") -> N107 | E13: =IFERROR(PRODUCTS!E12,"") -> Camera | F13: =IFERROR(PRODUCTS!F12,"") -> 52000 | G13: =SUMIF(Table4[Product_Name],Table6[[#This Row],[Product_Name]],Table4[Units]) -> 20 | H13: =SUMIF(salesdata[Product_Name],Table6[[#This Row],[Product_Name]],salesdata[Units]) -> 7 | I13: =Table6[[#This Row],[Purchased Units]]-Table6[[#This Row],[Sold Units]] -> 13 | J13: =Table6[[#This Row],[Cost]]*Table6[[#This Row],[Stock]] -> 676000 | K13: =IF(Table6[[#This Row],[Stock]]<5,"📞 "&Table6[[#This Row],[Product_Name]]&" Needs to re-order ! Ph "&VLOOKUP(Table6[[#This Row],[Product_Code]],Table3[#All],4,0),"")
D14: =IFERROR(PRODUCTS!D13,"") -> N108 | E14: =IFERROR(PRODUCTS!E13,"") -> Headphone | F14: =IFERROR(PRODUCTS!F13,"") -> 790 | G14: =SUMIF(Table4[Product_Name],Table6[[#This Row],[Product_Name]],Table4[Units]) -> 35 | H14: =SUMIF(salesdata[Product_Name],Table6[[#This Row],[Product_Name]],salesdata[Units]) -> 1 | I14: =Table6[[#This Row],[Purchased Units]]-Table6[[#This Row],[Sold Units]] -> 34 | J14: =Table6[[#This Row],[Cost]]*Table6[[#This Row],[Stock]] -> 26860 | K14: =IF(Table6[[#This Row],[Stock]]<5,"📞 "&Table6[[#This Row],[Product_Name]]&" Needs to re-order ! Ph "&VLOOKUP(Table6[[#This Row],[Product_Code]],Table3[#All],4,0),"")
D15: =IFERROR(PRODUCTS!D14,"") -> N109 | E15: =IFERROR(PRODUCTS!E14,"") -> Speakers | F15: =IFERROR(PRODUCTS!F14,"") -> 1750 | G15: =SUMIF(Table4[Product_Name],Table6[[#This Row],[Product_Name]],Table4[Units]) -> 14 | H15: =SUMIF(salesdata[Product_Name],Table6[[#This Row],[Product_Name]],salesdata[Units]) -> 2 | I15: =Table6[[#This Row],[Purchased Units]]-Table6[[#This Row],[Sold Units]] -> 12 | J15: =Table6[[#This Row],[Cost]]*Table6[[#This Row],[Stock]] -> 21000 | K15: =IF(Table6[[#This Row],[Stock]]<5,"📞 "&Table6[[#This Row],[Product_Name]]&" Needs to re-order ! Ph "&VLOOKUP(Table6[[#This Row],[Product_Code]],Table3[#All],4,0),"")
D16: =IFERROR(PRODUCTS!D15,"") -> N110 | E16: =IFERROR(PRODUCTS!E15,"") -> Tablets | F16: =IFERROR(PRODUCTS!F15,"") -> 23500 | G16: =SUMIF(Table4[Product_Name],Table6[[#This Row],[Product_Name]],Table4[Units]) -> 23 | H16: =SUMIF(salesdata[Product_Name],Table6[[#This Row],[Product_Name]],salesdata[Units]) -> 2 | I16: =Table6[[#This Row],[Purchased Units]]-Table6[[#This Row],[Sold Units]] -> 21 | J16: =Table6[[#This Row],[Cost]]*Table6[[#This Row],[Stock]] -> 493500 | K16: =IF(Table6[[#This Row],[Stock]]<5,"📞 "&Table6[[#This Row],[Product_Name]]&" Needs to re-order ! Ph "&VLOOKUP(Table6[[#This Row],[Product_Code]],Table3[#All],4,0),"")
D17: =IFERROR(PRODUCTS!D16,"") -> N111 | E17: =IFERROR(PRODUCTS!E16,"") -> Adopter | F17: =IFERROR(PRODUCTS!F16,"") -> 1250 | G17: =SUMIF(Table4[Product_Name],Table6[[#This Row],[Product_Name]],Table4[Units]) -> 10 | H17: =SUMIF(salesdata[Product_Name],Table6[[#This Row],[Product_Name]],salesdata[Units]) -> 6 | I17: =Table6[[#This Row],[Purchased Units]]-Table6[[#This Row],[Sold Units]] -> 4 | J17: =Table6[[#This Row],[Cost]]*Table6[[#This Row],[Stock]] -> 5000 | K17: =IF(Table6[[#This Row],[Stock]]<5,"📞 "&Table6[[#This Row],[Product_Name]]&" Needs to re-order ! Ph "&VLOOKUP(Table6[[#This Row],[Product_Code]],Table3[#All],4,0),"") -> 📞 Adopter Needs to re-order ! Ph 0317xxxxxxxx
D18: =IFERROR(PRODUCTS!D17,"") -> N112 | E18: =IFERROR(PRODUCTS!E17,"") -> Wireless Mouse | F18: =IFERROR(PRODUCTS!F17,"") -> 2500 | G18: =SUMIF(Table4[Product_Name],Table6[[#This Row],[Product_Name]],Table4[Units]) -> 57 | H18: =SUMIF(salesdata[Product_Name],Table6[[#This Row],[Product_Name]],salesdata[Units]) -> 3 | I18: =Table6[[#This Row],[Purchased Units]]-Table6[[#This Row],[Sold Units]] -> 54 | J18: =Table6[[#This Row],[Cost]]*Table6[[#This Row],[Stock]] -> 135000 | K18: =IF(Table6[[#This Row],[Stock]]<5,"📞 "&Table6[[#This Row],[Product_Name]]&" Needs to re-order ! Ph "&VLOOKUP(Table6[[#This Row],[Product_Code]],Table3[#All],4,0),"")
... D24: =IFERROR(PRODUCTS!D23,"") -> N119 | E24: =IFERROR(PRODUCTS!E23,"") -> Iphone 14 | F24: =IFERROR(PRODUCTS!F23,"") -> 130000 | G24: =SUMIF(Table4[Product_Name],Table6[[#This Row],[Product_Name]],Table4[Units]) -> 16 | H24: =SUMIF(salesdata[Product_Name],Table6[[#This Row],[Product_Name]],salesdata[Units]) -> 3 | I24: =Table6[[#This Row],[Purchased Units]]-Table6[[#This Row],[Sold Units]] -> 13 | J24: =Table6[[#This Row],[Cost]]*Table6[[#This Row],[Stock]] -> 1690000 | K24: =IF(Table6[[#This Row],[Stock]]<5,"📞 "&Table6[[#This Row],[Product_Name]]&" Needs to re-order ! Ph "&VLOOKUP(Table6[[#This Row],[Product_Code]],Table3[#All],4,0),"")

Sheet PIVOTS
B2: Count of Cust_Name | C2: Count of Product_Name | D2: Sum of Amount | E2: Sum of Amount | F2: Sum of Stock Amount | H2: Products | I2: Sum of Stock
B3: 8 | C3: 18 | D3: 12537200 | E3: 3044450 | F3: 10453460 | H3: Adopter | I3: 4
H4: Apple Watch | I4: 22
B5: Number Of Customers | C5: Number Of Products | D5: Purchased Amount | E5: Sales Amount | F5: Stock Amount | H5: Camera | I5: 13
B6: =GETPIVOTDATA("Cust_Name",$B$2) -> 8 | C6: =GETPIVOTDATA("Product_Name",$C$2) -> 18 | D6: =GETPIVOTDATA("Amount",$D$2) -> 12537200 | E6: =GETPIVOTDATA("Amount",$E$2) -> 3044450 | F6: =GETPIVOTDATA("Stock Amount",$F$2) -> 10453460 | H6: Charger | I6: 46
H7: Desktop | I7: 4
H8: Headphone | I8: 34
B9: Products | C9: Units Sold | D9: Customer Name | E9: Sales | F9: Profit / Loss | H9: Laptop HP | I9: 4
B10: Laptop HP | C10: 11 | D10: Qsim | E10: 795000 | H10: Lightening Cable | I10: 34
B11: Wireless Printer | C11: 8 | D11: Bilal | E11: 690250 | F11: =F6+E6-D6 -> 960710 | H11: Macbook | I11: 24
B12: Camera | C12: 7 | D12: Ali | E12: 565000 | H12: Mouse | I12: 23
B13: Adopter | C13: 6 | D13: Waleed | E13: 537000 | H13: Rgb Keyboard | I13: 29
B14: Desktop | C14: 6 | D14: Hamid | E14: 349000 | H14: Smart Watch | I14: 59
B15: Grand Total | C15: 38 | D15: Grand Total | E15: 2936250 | H15: Speakers | I15: 12
H16: Tablets | I16: 21
H17: Wireless Mouse | I17: 54
H18: Wireless Printer | I18: 4
H19: Iphone 13 | I19: 23
H20: Iphone 14 | I20: 13
H21: Grand Total | I21: 423
